help_to_click/__init__.py
help_to_click/core/__init__.py
help_to_click/core/config.py
help_to_click/core/helper.py
help_to_click/core/spec.py
help_to_click/std/__init__.py
help_to_click/std/factory.py
help_to_click/std/parser.py
help_to_click/std/standard.py
help_to_click/utils/__init__.py
help_to_click/utils/generated.py
help_to_click-0.1.0.dist-info/WHEEL
help_to_click-0.1.0.dist-info/METADATA
help_to_click-0.1.0.dist-info/RECORD
