Metadata-Version: 2.3
Name: help-to-click
Version: 0.1.0
Summary: Parse CLI help text and generate Click commands, plain Python functions, or standalone CLI files
Keywords: cli,click,parser,code-generation,command-line
Author: ZackaryW
Author-email: ZackaryW <36378555+ZackaryW@users.noreply.github.com>
License: MIT License
Classifier: Development Status :: 4 - Beta
Classifier: Intended Audience :: Developers
Classifier: License :: OSI Approved :: MIT License
Classifier: Programming Language :: Python :: 3
Classifier: Programming Language :: Python :: 3.12
Classifier: Topic :: Software Development :: Libraries :: Python Modules
Classifier: Topic :: Software Development :: Code Generators
Classifier: Topic :: System :: Systems Administration
Requires-Dist: click>=8.0.0
Requires-Python: >=3.12
Project-URL: Homepage, https://github.com/ZackaryW/help_to_click
Project-URL: Issues, https://github.com/ZackaryW/help_to_click/issues
Project-URL: Repository, https://github.com/ZackaryW/help_to_click
